LICENSE
MANIFEST.in
README.md
scrapy.cfg
setup.cfg
setup.py
os_scrapy_random_useragent/__init__.py
os_scrapy_random_useragent/items.py
os_scrapy_random_useragent/middlewares.py
os_scrapy_random_useragent/pipelines.py
os_scrapy_random_useragent/settings.py
os_scrapy_random_useragent.egg-info/PKG-INFO
os_scrapy_random_useragent.egg-info/SOURCES.txt
os_scrapy_random_useragent.egg-info/dependency_links.txt
os_scrapy_random_useragent.egg-info/not-zip-safe
os_scrapy_random_useragent.egg-info/requires.txt
os_scrapy_random_useragent.egg-info/top_level.txt
os_scrapy_random_useragent/spiders/__init__.py
requirements/requirements-lint.txt
requirements/requirements-test.txt
requirements/requirements.txt
tests/__init__.py
tests/test_scrapy_check.py
useragents/mobile.lst
useragents/pc.lst